{"_default": {"1": {"BITICOIN": {"ULTIMA_TRANS": "35024.16", "COMPRA": "35024.16", "VENDA": "35100", "DATA": "2019-10-10 13:36:16", "STATUS": "-"}}, "2": {"DOLAR": {"ULTIMA_TRANS": "4.11", "COMPRA": "-", "VENDA": "-", "DATA": "2019-10-10 10:06:58", "STATUS": "-"}}, "3": {"EURO": {"ULTIMA_TRANS": "4.53", "COMPRA": "-", "VENDA": "-", "DATA": "2019-10-10 10:06:57", "STATUS": "-"}}, "4": {"BITICOIN": {"ULTIMA_TRANS": "35024.15", "COMPRA": "35024.17", "VENDA": "35100", "DATA": "2019-10-10 13:37:05", "STATUS": "-"}}, "5": {"DOLAR": {"ULTIMA_TRANS": "4.11", "COMPRA": "-", "VENDA": "-", "DATA": "2019-10-10 10:36:08", "STATUS": "-"}}, "6": {"EURO": {"ULTIMA_TRANS": "4.54", "COMPRA": "-", "VENDA": "-", "DATA": "2019-10-10 10:36:07", "STATUS": "-"}}, "7": {"BITICOIN": {"ULTIMA_TRANS": "35100.0", "COMPRA": "35024.18", "VENDA": "35100", "DATA": "2019-10-10 13:38:20", "STATUS": "-"}}, "8": {"DOLAR": {"ULTIMA_TRANS": "4.11", "COMPRA": "-", "VENDA": "-", "DATA": "2019-10-10 10:36:08", "STATUS": "-"}}, "9": {"EURO": {"ULTIMA_TRANS": "4.54", "COMPRA": "-", "VENDA": "-", "DATA": "2019-10-10 10:36:07", "STATUS": "-"}}, "10": {"BITICOIN": {"ULTIMA_TRANS": "35024.17", "COMPRA": "35024.2", "VENDA": "35199", "DATA": "2019-10-10 13:39:20", "STATUS": "-"}}, "11": {"DOLAR": {"ULTIMA_TRANS": "4.11", "COMPRA": "-", "VENDA": "-", "DATA": "2019-10-10 10:36:08", "STATUS": "-"}}, "12": {"EURO": {"ULTIMA_TRANS": "4.54", "COMPRA": "-", "VENDA": "-", "DATA": "2019-10-10 10:36:07", "STATUS": "-"}}, "13": {"BITICOIN": {"ULTIMA_TRANS": "35023.3", "COMPRA": "35023.33", "VENDA": "35199", "DATA": "2019-10-10 13:40:14", "STATUS": "-"}}, "14": {"DOLAR": {"ULTIMA_TRANS": "4.11", "COMPRA": "-", "VENDA": "-", "DATA": "2019-10-10 10:39:16", "STATUS": "-"}}, "15": {"EURO": {"ULTIMA_TRANS": "4.54", "COMPRA": "-", "VENDA": "-", "DATA": "2019-10-10 10:39:18", "STATUS": "-"}}, "16": {"BITICOIN": {"ULTIMA_TRANS": "35023.3", "COMPRA": "35023.3", "VENDA": "35199", "DATA": "2019-10-10 13:41:11", "STATUS": "-"}}, "17": {"DOLAR": {"ULTIMA_TRANS": "4.11", "COMPRA": "-", "VENDA": "-", "DATA": "2019-10-10 10:39:16", "STATUS": "-"}}, "18": {"EURO": {"ULTIMA_TRANS": "4.54", "COMPRA": "-", "VENDA": "-", "DATA": "2019-10-10 10:39:18", "STATUS": "-"}}, "19": {"BITICOIN": {"ULTIMA_TRANS": "35023.31", "COMPRA": "35050.01", "VENDA": "35199", "DATA": "2019-10-10 13:42:18", "STATUS": "-"}}, "20": {"DOLAR": {"ULTIMA_TRANS": "4.11", "COMPRA": "-", "VENDA": "-", "DATA": "2019-10-10 10:39:16", "STATUS": "-"}}, "21": {"EURO": {"ULTIMA_TRANS": "4.54", "COMPRA": "-", "VENDA": "-", "DATA": "2019-10-10 10:39:18", "STATUS": "-"}}, "22": {"BITICOIN": {"ULTIMA_TRANS": "35050.01", "COMPRA": "35060", "VENDA": "35199", "DATA": "2019-10-10 13:43:18", "STATUS": "-"}}, "23": {"DOLAR": {"ULTIMA_TRANS": "4.11", "COMPRA": "-", "VENDA": "-", "DATA": "2019-10-10 10:39:16", "STATUS": "-"}}, "24": {"EURO": {"ULTIMA_TRANS": "4.54", "COMPRA": "-", "VENDA": "-", "DATA": "2019-10-10 10:39:18", "STATUS": "-"}}, "25": {"BITICOIN": {"ULTIMA_TRANS": "35060.0", "COMPRA": "35060", "VENDA": "35199", "DATA": "2019-10-10 13:44:09", "STATUS": "-"}}, "26": {"DOLAR": {"ULTIMA_TRANS": "4.11", "COMPRA": "-", "VENDA": "-", "DATA": "2019-10-10 10:42:07", "STATUS": "-"}}, "27": {"EURO": {"ULTIMA_TRANS": "4.54", "COMPRA": "-", "VENDA": "-", "DATA": "2019-10-10 10:42:08", "STATUS": "-"}}, "28": {"BITICOIN": {"ULTIMA_TRANS": "35060.0", "COMPRA": "35060", "VENDA": "35199", "DATA": "2019-10-10 13:45:15", "STATUS": "-"}}, "29": {"DOLAR": {"ULTIMA_TRANS": "4.11", "COMPRA": "-", "VENDA": "-", "DATA": "2019-10-10 10:42:07", "STATUS": "-"}}, "30": {"EURO": {"ULTIMA_TRANS": "4.54", "COMPRA": "-", "VENDA": "-", "DATA": "2019-10-10 10:42:08", "STATUS": "-"}}, "31": {"BITICOIN": {"ULTIMA_TRANS": "35051.83", "COMPRA": "35051.83", "VENDA": "35199", "DATA": "2019-10-10 13:46:23", "STATUS": "-"}}, "32": {"DOLAR": {"ULTIMA_TRANS": "4.11", "COMPRA": "-", "VENDA": "-", "DATA": "2019-10-10 10:42:07", "STATUS": "-"}}, "33": {"EURO": {"ULTIMA_TRANS": "4.54", "COMPRA": "-", "VENDA": "-", "DATA": "2019-10-10 10:42:08", "STATUS": "-"}}, "34": {"BITICOIN": {"ULTIMA_TRANS": "35051.83", "COMPRA": "35065", "VENDA": "35199", "DATA": "2019-10-10 13:47:09", "STATUS": "-"}}, "35": {"DOLAR": {"ULTIMA_TRANS": "4.11", "COMPRA": "-", "VENDA": "-", "DATA": "2019-10-10 10:42:07", "STATUS": "-"}}, "36": {"EURO": {"ULTIMA_TRANS": "4.54", "COMPRA": "-", "VENDA": "-", "DATA": "2019-10-10 10:42:08", "STATUS": "-"}}, "37": {"BITICOIN": {"ULTIMA_TRANS": "35051.83", "COMPRA": "35065", "VENDA": "35199", "DATA": "2019-10-10 13:48:12", "STATUS": "-"}}, "38": {"DOLAR": {"ULTIMA_TRANS": "4.11", "COMPRA": "-", "VENDA": "-", "DATA": "2019-10-10 10:45:14", "STATUS": "-"}}, "39": {"EURO": {"ULTIMA_TRANS": "4.54", "COMPRA": "-", "VENDA": "-", "DATA": "2019-10-10 10:45:13", "STATUS": "-"}}, "40": {"BITICOIN": {"ULTIMA_TRANS": "35199.0", "COMPRA": "35065.01", "VENDA": "35199", "DATA": "2019-10-10 13:49:12", "STATUS": "-"}}, "41": {"DOLAR": {"ULTIMA_TRANS": "4.11", "COMPRA": "-", "VENDA": "-", "DATA": "2019-10-10 10:45:14", "STATUS": "-"}}, "42": {"EURO": {"ULTIMA_TRANS": "4.54", "COMPRA": "-", "VENDA": "-", "DATA": "2019-10-10 10:45:13", "STATUS": "-"}}, "43": {"BITICOIN": {"ULTIMA_TRANS": "35199.0", "COMPRA": "35065.01", "VENDA": "35199", "DATA": "2019-10-10 13:50:17", "STATUS": "-"}}, "44": {"DOLAR": {"ULTIMA_TRANS": "4.11", "COMPRA": "-", "VENDA": "-", "DATA": "2019-10-10 10:45:14", "STATUS": "-"}}, "45": {"EURO": {"ULTIMA_TRANS": "4.54", "COMPRA": "-", "VENDA": "-", "DATA": "2019-10-10 10:45:13", "STATUS": "-"}}, "46": {"BITICOIN": {"ULTIMA_TRANS": "35065.01", "COMPRA": "35065.01", "VENDA": "35199", "DATA": "2019-10-10 13:51:19", "STATUS": "-"}}, "47": {"DOLAR": {"ULTIMA_TRANS": "4.11", "COMPRA": "-", "VENDA": "-", "DATA": "2019-10-10 10:50:21", "STATUS": "-"}}, "48": {"EURO": {"ULTIMA_TRANS": "4.54", "COMPRA": "-", "VENDA": "-", "DATA": "2019-10-10 10:50:23", "STATUS": "-"}}, "49": {"BITICOIN": {"ULTIMA_TRANS": "35065.01", "COMPRA": "35065.01", "VENDA": "35199", "DATA": "2019-10-10 13:52:19", "STATUS": "-"}}, "50": {"DOLAR": {"ULTIMA_TRANS": "4.11", "COMPRA": "-", "VENDA": "-", "DATA": "2019-10-10 10:50:21", "STATUS": "-"}}, "51": {"EURO": {"ULTIMA_TRANS": "4.54", "COMPRA": "-", "VENDA": "-", "DATA": "2019-10-10 10:50:23", "STATUS": "-"}}, "52": {"BITICOIN": {"ULTIMA_TRANS": "35000.0", "COMPRA": "35000", "VENDA": "35199", "DATA": "2019-10-10 13:53:20", "STATUS": "-"}}, "53": {"DOLAR": {"ULTIMA_TRANS": "4.11", "COMPRA": "-", "VENDA": "-", "DATA": "2019-10-10 10:50:21", "STATUS": "-"}}, "54": {"EURO": {"ULTIMA_TRANS": "4.54", "COMPRA": "-", "VENDA": "-", "DATA": "2019-10-10 10:50:23", "STATUS": "-"}}, "55": {"BITICOIN": {"ULTIMA_TRANS": "35000.02", "COMPRA": "35000.02", "VENDA": "35199", "DATA": "2019-10-10 13:54:25", "STATUS": "-"}}, "56": {"DOLAR": {"ULTIMA_TRANS": "4.11", "COMPRA": "-", "VENDA": "-", "DATA": "2019-10-10 10:51:20", "STATUS": "-"}}, "57": {"EURO": {"ULTIMA_TRANS": "4.54", "COMPRA": "-", "VENDA": "-", "DATA": "2019-10-10 10:51:17", "STATUS": "-"}}, "58": {"BITICOIN": {"ULTIMA_TRANS": "35000.02", "COMPRA": "35000.02", "VENDA": "35199", "DATA": "2019-10-10 13:55:26", "STATUS": "-"}}, "59": {"DOLAR": {"ULTIMA_TRANS": "4.11", "COMPRA": "-", "VENDA": "-", "DATA": "2019-10-10 10:51:20", "STATUS": "-"}}, "60": {"EURO": {"ULTIMA_TRANS": "4.54", "COMPRA": "-", "VENDA": "-", "DATA": "2019-10-10 10:51:17", "STATUS": "-"}}, "61": {"BITICOIN": {"ULTIMA_TRANS": "35225.0", "COMPRA": "35000.05", "VENDA": "35200", "DATA": "2019-10-10 13:56:26", "STATUS": "-"}}, "62": {"DOLAR": {"ULTIMA_TRANS": "4.11", "COMPRA": "-", "VENDA": "-", "DATA": "2019-10-10 10:51:20", "STATUS": "-"}}, "63": {"EURO": {"ULTIMA_TRANS": "4.54", "COMPRA": "-", "VENDA": "-", "DATA": "2019-10-10 10:51:17", "STATUS": "-"}}, "64": {"BITICOIN": {"ULTIMA_TRANS": "35295.5", "COMPRA": "35000.35", "VENDA": "35295.45", "DATA": "2019-10-10 13:57:16", "STATUS": "-"}}, "65": {"DOLAR": {"ULTIMA_TRANS": "4.11", "COMPRA": "-", "VENDA": "-", "DATA": "2019-10-10 10:53:56", "STATUS": "-"}}, "66": {"EURO": {"ULTIMA_TRANS": "4.54", "COMPRA": "-", "VENDA": "-", "DATA": "2019-10-10 10:53:53", "STATUS": "-"}}, "67": {"BITICOIN": {"ULTIMA_TRANS": "35295.5", "COMPRA": "35000.35", "VENDA": "35295.45", "DATA": "2019-10-10 13:58:18", "STATUS": "-"}}, "68": {"DOLAR": {"ULTIMA_TRANS": "4.11", "COMPRA": "-", "VENDA": "-", "DATA": "2019-10-10 10:53:56", "STATUS": "-"}}, "69": {"EURO": {"ULTIMA_TRANS": "4.54", "COMPRA": "-", "VENDA": "-", "DATA": "2019-10-10 10:53:53", "STATUS": "-"}}, "70": {"BITICOIN": {"ULTIMA_TRANS": "35011.3", "COMPRA": "35011.33", "VENDA": "35295.17", "DATA": "2019-10-10 13:59:18", "STATUS": "-"}}, "71": {"DOLAR": {"ULTIMA_TRANS": "4.11", "COMPRA": "-", "VENDA": "-", "DATA": "2019-10-10 10:53:56", "STATUS": "-"}}, "72": {"EURO": {"ULTIMA_TRANS": "4.54", "COMPRA": "-", "VENDA": "-", "DATA": "2019-10-10 10:53:53", "STATUS": "-"}}, "73": {"BITICOIN": {"ULTIMA_TRANS": "35000.0", "COMPRA": "35012", "VENDA": "35100", "DATA": "2019-10-10 14:00:22", "STATUS": "-"}}, "74": {"DOLAR": {"ULTIMA_TRANS": "4.11", "COMPRA": "-", "VENDA": "-", "DATA": "2019-10-10 10:53:56", "STATUS": "-"}}, "75": {"EURO": {"ULTIMA_TRANS": "4.54", "COMPRA": "-", "VENDA": "-", "DATA": "2019-10-10 10:53:53", "STATUS": "-"}}, "76": {"BITICOIN": {"ULTIMA_TRANS": "35012.0", "COMPRA": "35012", "VENDA": "35199", "DATA": "2019-10-10 14:01:19", "STATUS": "-"}}, "77": {"DOLAR": {"ULTIMA_TRANS": "4.11", "COMPRA": "-", "VENDA": "-", "DATA": "2019-10-10 11:00:25", "STATUS": "-"}}, "78": {"EURO": {"ULTIMA_TRANS": "4.54", "COMPRA": "-", "VENDA": "-", "DATA": "2019-10-10 11:00:27", "STATUS": "-"}}, "79": {"BITICOIN": {"ULTIMA_TRANS": "35000.0", "COMPRA": "35000", "VENDA": "35199", "DATA": "2019-10-10 14:02:24", "STATUS": "-"}}, "80": {"DOLAR": {"ULTIMA_TRANS": "4.11", "COMPRA": "-", "VENDA": "-", "DATA": "2019-10-10 11:00:25", "STATUS": "-"}}, "81": {"EURO": {"ULTIMA_TRANS": "4.54", "COMPRA": "-", "VENDA": "-", "DATA": "2019-10-10 11:00:27", "STATUS": "-"}}, "82": {"BITICOIN": {"ULTIMA_TRANS": "35199.0", "COMPRA": "35000", "VENDA": "35199", "DATA": "2019-10-10 14:03:29", "STATUS": "-"}}, "83": {"DOLAR": {"ULTIMA_TRANS": "4.11", "COMPRA": "-", "VENDA": "-", "DATA": "2019-10-10 11:00:25", "STATUS": "-"}}, "84": {"EURO": {"ULTIMA_TRANS": "4.54", "COMPRA": "-", "VENDA": "-", "DATA": "2019-10-10 11:00:27", "STATUS": "-"}}, "85": {"BITICOIN": {"ULTIMA_TRANS": "35199.0", "COMPRA": "35000", "VENDA": "35199", "DATA": "2019-10-10 14:04:17", "STATUS": "-"}}, "86": {"DOLAR": {"ULTIMA_TRANS": "4.11", "COMPRA": "-", "VENDA": "-", "DATA": "2019-10-10 11:03:30", "STATUS": "-"}}, "87": {"EURO": {"ULTIMA_TRANS": "4.54", "COMPRA": "-", "VENDA": "-", "DATA": "2019-10-10 11:03:27", "STATUS": "-"}}, "88": {"BITICOIN": {"ULTIMA_TRANS": "35199.0", "COMPRA": "35000", "VENDA": "35199", "DATA": "2019-10-10 14:05:17", "STATUS": "-"}}, "89": {"DOLAR": {"ULTIMA_TRANS": "4.11", "COMPRA": "-", "VENDA": "-", "DATA": "2019-10-10 11:03:30", "STATUS": "-"}}, "90": {"EURO": {"ULTIMA_TRANS": "4.54", "COMPRA": "-", "VENDA": "-", "DATA": "2019-10-10 11:03:27", "STATUS": "-"}}, "91": {"BITICOIN": {"ULTIMA_TRANS": "35199.0", "COMPRA": "35000.01", "VENDA": "35199", "DATA": "2019-10-10 14:06:18", "STATUS": "-"}}, "92": {"DOLAR": {"ULTIMA_TRANS": "4.11", "COMPRA": "-", "VENDA": "-", "DATA": "2019-10-10 11:03:30", "STATUS": "-"}}, "93": {"EURO": {"ULTIMA_TRANS": "4.54", "COMPRA": "-", "VENDA": "-", "DATA": "2019-10-10 11:03:27", "STATUS": "-"}}, "94": {"BITICOIN": {"ULTIMA_TRANS": "35199.0", "COMPRA": "35000.01", "VENDA": "35199", "DATA": "2019-10-10 14:07:25", "STATUS": "-"}}, "95": {"DOLAR": {"ULTIMA_TRANS": "4.11", "COMPRA": "-", "VENDA": "-", "DATA": "2019-10-10 11:06:31", "STATUS": "-"}}, "96": {"EURO": {"ULTIMA_TRANS": "4.54", "COMPRA": "-", "VENDA": "-", "DATA": "2019-10-10 11:06:28", "STATUS": "-"}}, "97": {"BITICOIN": {"ULTIMA_TRANS": "35000.0", "COMPRA": "35010", "VENDA": "35199", "DATA": "2019-10-10 14:08:19", "STATUS": "-"}}, "98": {"DOLAR": {"ULTIMA_TRANS": "4.11", "COMPRA": "-", "VENDA": "-", "DATA": "2019-10-10 11:06:31", "STATUS": "-"}}, "99": {"EURO": {"ULTIMA_TRANS": "4.54", "COMPRA": "-", "VENDA": "-", "DATA": "2019-10-10 11:06:28", "STATUS": "-"}}, "100": {"BITICOIN": {"ULTIMA_TRANS": "35349.92", "COMPRA": "35010.03", "VENDA": "35349.88", "DATA": "2019-10-10 14:09:22", "STATUS": "-"}}, "101": {"DOLAR": {"ULTIMA_TRANS": "4.11", "COMPRA": "-", "VENDA": "-", "DATA": "2019-10-10 11:06:31", "STATUS": "-"}}, "102": {"EURO": {"ULTIMA_TRANS": "4.54", "COMPRA": "-", "VENDA": "-", "DATA": "2019-10-10 11:06:28", "STATUS": "-"}}, "103": {"BITICOIN": {"ULTIMA_TRANS": "35000.03", "COMPRA": "35173.61", "VENDA": "35347.88", "DATA": "2019-10-10 14:10:31", "STATUS": "-"}}, "104": {"DOLAR": {"ULTIMA_TRANS": "4.11", "COMPRA": "-", "VENDA": "-", "DATA": "2019-10-10 11:06:55", "STATUS": "-"}}, "105": {"EURO": {"ULTIMA_TRANS": "4.54", "COMPRA": "-", "VENDA": "-", "DATA": "2019-10-10 11:06:57", "STATUS": "-"}}, "106": {"BITICOIN": {"ULTIMA_TRANS": "35050.01", "COMPRA": "35050.01", "VENDA": "35200", "DATA": "2019-10-10 14:11:30", "STATUS": "-"}}, "107": {"DOLAR": {"ULTIMA_TRANS": "4.11", "COMPRA": "-", "VENDA": "-", "DATA": "2019-10-10 11:06:55", "STATUS": "-"}}, "108": {"EURO": {"ULTIMA_TRANS": "4.54", "COMPRA": "-", "VENDA": "-", "DATA": "2019-10-10 11:06:57", "STATUS": "-"}}, "109": {"BITICOIN": {"ULTIMA_TRANS": "35050.01", "COMPRA": "35050.01", "VENDA": "35200", "DATA": "2019-10-10 14:12:22", "STATUS": "-"}}, "110": {"DOLAR": {"ULTIMA_TRANS": "4.11", "COMPRA": "-", "VENDA": "-", "DATA": "2019-10-10 11:06:55", "STATUS": "-"}}, "111": {"EURO": {"ULTIMA_TRANS": "4.54", "COMPRA": "-", "VENDA": "-", "DATA": "2019-10-10 11:06:57", "STATUS": "-"}}, "112": {"BITICOIN": {"ULTIMA_TRANS": "35080.0", "COMPRA": "35080", "VENDA": "35200", "DATA": "2019-10-10 14:13:25", "STATUS": "-"}}, "113": {"DOLAR": {"ULTIMA_TRANS": "4.11", "COMPRA": "-", "VENDA": "-", "DATA": "2019-10-10 11:06:55", "STATUS": "-"}}, "114": {"EURO": {"ULTIMA_TRANS": "4.54", "COMPRA": "-", "VENDA": "-", "DATA": "2019-10-10 11:06:57", "STATUS": "-"}}, "115": {"BITICOIN": {"ULTIMA_TRANS": "35080.0", "COMPRA": "35080", "VENDA": "35200", "DATA": "2019-10-10 14:14:32", "STATUS": "-"}}, "116": {"DOLAR": {"ULTIMA_TRANS": "4.11", "COMPRA": "-", "VENDA": "-", "DATA": "2019-10-10 11:13:35", "STATUS": "-"}}, "117": {"EURO": {"ULTIMA_TRANS": "4.54", "COMPRA": "-", "VENDA": "-", "DATA": "2019-10-10 11:13:32", "STATUS": "-"}}, "118": {"BITICOIN": {"ULTIMA_TRANS": "35080.0", "COMPRA": "35080", "VENDA": "35199", "DATA": "2019-10-10 14:15:25", "STATUS": "-"}}, "119": {"DOLAR": {"ULTIMA_TRANS": "4.11", "COMPRA": "-", "VENDA": "-", "DATA": "2019-10-10 11:13:35", "STATUS": "-"}}, "120": {"EURO": {"ULTIMA_TRANS": "4.54", "COMPRA": "-", "VENDA": "-", "DATA": "2019-10-10 11:13:32", "STATUS": "-"}}, "121": {"BITICOIN": {"ULTIMA_TRANS": "35080.0", "COMPRA": "35080", "VENDA": "35198.99", "DATA": "2019-10-10 14:16:31", "STATUS": "-"}}, "122": {"DOLAR": {"ULTIMA_TRANS": "4.11", "COMPRA": "-", "VENDA": "-", "DATA": "2019-10-10 11:13:35", "STATUS": "-"}}, "123": {"EURO": {"ULTIMA_TRANS": "4.54", "COMPRA": "-", "VENDA": "-", "DATA": "2019-10-10 11:13:32", "STATUS": "-"}}, "124": {"BITICOIN": {"ULTIMA_TRANS": "35080.0", "COMPRA": "35080", "VENDA": "35198.99", "DATA": "2019-10-10 14:17:23", "STATUS": "-"}}, "125": {"DOLAR": {"ULTIMA_TRANS": "4.11", "COMPRA": "-", "VENDA": "-", "DATA": "2019-10-10 11:16:25", "STATUS": "-"}}, "126": {"EURO": {"ULTIMA_TRANS": "4.54", "COMPRA": "-", "VENDA": "-", "DATA": "2019-10-10 11:16:23", "STATUS": "-"}}, "127": {"BITICOIN": {"ULTIMA_TRANS": "35080.0", "COMPRA": "35080", "VENDA": "35198.99", "DATA": "2019-10-10 14:18:22", "STATUS": "-"}}, "128": {"DOLAR": {"ULTIMA_TRANS": "4.11", "COMPRA": "-", "VENDA": "-", "DATA": "2019-10-10 11:16:25", "STATUS": "-"}}, "129": {"EURO": {"ULTIMA_TRANS": "4.54", "COMPRA": "-", "VENDA": "-", "DATA": "2019-10-10 11:16:23", "STATUS": "-"}}, "130": {"BITICOIN": {"ULTIMA_TRANS": "35199.0", "COMPRA": "35080", "VENDA": "35199", "DATA": "2019-10-10 14:19:36", "STATUS": "-"}}, "131": {"DOLAR": {"ULTIMA_TRANS": "4.11", "COMPRA": "-", "VENDA": "-", "DATA": "2019-10-10 11:16:25", "STATUS": "-"}}, "132": {"EURO": {"ULTIMA_TRANS": "4.54", "COMPRA": "-", "VENDA": "-", "DATA": "2019-10-10 11:16:23", "STATUS": "-"}}, "133": {"BITICOIN": {"ULTIMA_TRANS": "35080.0", "COMPRA": "35080", "VENDA": "35199", "DATA": "2019-10-10 14:20:31", "STATUS": "-"}}, "134": {"DOLAR": {"ULTIMA_TRANS": "4.11", "COMPRA": "-", "VENDA": "-", "DATA": "2019-10-10 11:16:25", "STATUS": "-"}}, "135": {"EURO": {"ULTIMA_TRANS": "4.54", "COMPRA": "-", "VENDA": "-", "DATA": "2019-10-10 11:16:23", "STATUS": "-"}}, "136": {"BITICOIN": {"ULTIMA_TRANS": "35080.0", "COMPRA": "35080", "VENDA": "35199", "DATA": "2019-10-10 14:21:38", "STATUS": "-"}}, "137": {"DOLAR": {"ULTIMA_TRANS": "4.11", "COMPRA": "-", "VENDA": "-", "DATA": "2019-10-10 11:19:51", "STATUS": "-"}}, "138": {"EURO": {"ULTIMA_TRANS": "4.54", "COMPRA": "-", "VENDA": "-", "DATA": "2019-10-10 11:19:52", "STATUS": "-"}}, "139": {"BITICOIN": {"ULTIMA_TRANS": "35080.0", "COMPRA": "35080", "VENDA": "35198.97", "DATA": "2019-10-10 14:22:29", "STATUS": "-"}}, "140": {"DOLAR": {"ULTIMA_TRANS": "4.11", "COMPRA": "-", "VENDA": "-", "DATA": "2019-10-10 11:19:51", "STATUS": "-"}}, "141": {"EURO": {"ULTIMA_TRANS": "4.54", "COMPRA": "-", "VENDA": "-", "DATA": "2019-10-10 11:19:52", "STATUS": "-"}}, "142": {"BITICOIN": {"ULTIMA_TRANS": "35199.0", "COMPRA": "35080", "VENDA": "35199", "DATA": "2019-10-10 14:23:32", "STATUS": "-"}}, "143": {"DOLAR": {"ULTIMA_TRANS": "4.11", "COMPRA": "-", "VENDA": "-", "DATA": "2019-10-10 11:19:51", "STATUS": "-"}}, "144": {"EURO": {"ULTIMA_TRANS": "4.54", "COMPRA": "-", "VENDA": "-", "DATA": "2019-10-10 11:19:52", "STATUS": "-"}}, "145": {"BITICOIN": {"ULTIMA_TRANS": "35199.0", "COMPRA": "35080", "VENDA": "35198.97", "DATA": "2019-10-10 14:24:31", "STATUS": "-"}}, "146": {"DOLAR": {"ULTIMA_TRANS": "4.11", "COMPRA": "-", "VENDA": "-", "DATA": "2019-10-10 11:22:28", "STATUS": "-"}}, "147": {"EURO": {"ULTIMA_TRANS": "4.54", "COMPRA": "-", "VENDA": "-", "DATA": "2019-10-10 11:22:32", "STATUS": "-"}}, "148": {"BITICOIN": {"ULTIMA_TRANS": "35199.0", "COMPRA": "35080", "VENDA": "35198.97", "DATA": "2019-10-10 14:25:28", "STATUS": "-"}}, "149": {"DOLAR": {"ULTIMA_TRANS": "4.11", "COMPRA": "-", "VENDA": "-", "DATA": "2019-10-10 11:22:28", "STATUS": "-"}}, "150": {"EURO": {"ULTIMA_TRANS": "4.54", "COMPRA": "-", "VENDA": "-", "DATA": "2019-10-10 11:22:32", "STATUS": "-"}}}}